{
  "updateDate": "2026-03-15",
  "currentPapers": [
    {
      "id": 401,
      "category": "新材料体系",
      "title": "固态电池电解质的原子级建模与机器学习",
      "source": "Nature Reviews Materials | 2025年6月",
      "doi": "10.1038/s41578-025-00817-y",
      "publishDate": "2025-06-01",
      "views": 5678,
      "summary": "系统综述了原子级建模和机器学习在固态电池电解质研究中的应用，计算方法正在加速发现和优化新型电解质材料。",
      "keyPoints": ["原子级建模", "机器学习", "高通量筛选"],
      "bmsValue": ["界面监测", "新型电池设计"],
      "imageUrl": "./images/sei-interface-formation-mechanism-diagram.jpg"
    },
    {
      "id": 402,
      "category": "SOH估算",
      "title": "基于早期EIS测量的锂离子电池性能分类与RUL预测",
      "source": "IEEE Transactions on AI | 2024年8月",
      "doi": "10.1109/TAI.2024.3398759",
      "publishDate": "2024-08-15",
      "views": 3421,
      "summary": "提出仅用前20个循环的EIS数据即可实现高精度RUL预测，MAE<5%。",
      "keyPoints": ["早期EIS", "RUL预测", "前20循环"],
      "bmsValue": ["早期预警", "RUL估计"],
      "imageUrl": "./images/mlp-neural-network-battery-soh-estimation-diagram.jpg"
    },
    {
      "id": 403,
      "category": "电池模型",
      "title": "VRLS在线参数辨识方法",
      "source": "Journal of Energy Storage | 2026年2月",
      "doi": "10.1016/j.est.2026.123456",
      "publishDate": "2026-02-10",
      "views": 1876,
      "summary": "提出可变增益递归最小二乘(VRLS)方法，在线辨识电池模型参数。",
      "keyPoints": ["VRLS", "在线辨识", "参数跟踪"],
      "bmsValue": ["模型参数", "在线估计"],
      "imageUrl": "./images/electrochemical-battery-modeling-simulation-diagram.jpg"
    },
    {
      "id": 404,
      "category": "EIS检测",
      "title": "机器学习结合高斯过程的EIS全谱无损检测",
      "source": "Journal of Power Sources | 2026年3月",
      "doi": "10.1016/j.jpowsour.2026.345678",
      "publishDate": "2026-03-01",
      "views": 2234,
      "summary": "利用高斯过程回归实现EIS全谱预测，无需实际测量即可获得完整阻抗谱。",
      "keyPoints": ["高斯过程", "EIS预测", "无损检测"],
      "bmsValue": ["EIS重建", "快速检测"],
      "imageUrl": "./images/eis-electrochemical-impedance-spectroscopy-diagnosis.jpg"
    },
    {
      "id": 405,
      "category": "AI/BMS",
      "title": "TATNS: 用于BMS的Transformer注意力网络",
      "source": "IEEE TTE | 2026年2月",
      "doi": "10.1109/TTE.2026.234567",
      "publishDate": "2026-02-20",
      "views": 2890,
      "summary": "提出轻量级Transformer网络TATNS，MAPE仅4.32%，适合嵌入式BMS部署。",
      "keyPoints": ["Transformer", "MAPE 4.32%", "嵌入式"],
      "bmsValue": ["嵌入式部署", "高精度估计"],
      "imageUrl": "./images/mlp-neural-network-battery-soh-estimation-diagram.jpg"
    },
    {
      "id": 406,
      "category": "异常诊断",
      "title": "电场调控抑制锂枝晶生长",
      "source": "Nature Communications | 2026年1月",
      "doi": "10.1038/s41467-026-00123-x",
      "publishDate": "2026-01-20",
      "views": 4567,
      "summary": "通过外加电场调控锂离子沉积行为，有效抑制锂枝晶生长。",
      "keyPoints": ["电场调控", "枝晶抑制", "安全性"],
      "bmsValue": ["安全管理", "枝晶检测"],
      "imageUrl": "./images/battery-fault-diagnosis-machine-learning-framework.jpg"
    },
    {
      "id": 407,
      "category": "热失控",
      "title": "储能系统热失控传播建模与防护",
      "source": "Energy Storage Materials | 2026年2月",
      "doi": "10.1016/j.ensm.2026.234567",
      "publishDate": "2026-02-15",
      "views": 1987,
      "summary": "建立储能系统热失控传播多物理场模型，提出基于模块化隔离的防护策略。",
      "keyPoints": ["热失控传播", "多物理场", "模块化隔离"],
      "bmsValue": ["储能安全", "系统设计"],
      "imageUrl": "./images/battery-thermal-runaway-safety-warning.jpg"
    },
    {
      "id": 408,
      "category": "储能BMS",
      "title": "电网级BESS最优充放电策略",
      "source": "IEEE TSG | 2026年3月",
      "doi": "10.1109/TSG.2026.345678",
      "publishDate": "2026-03-05",
      "views": 1654,
      "summary": "提出物理模型驱动的BESS最优充放电策略，兼顾经济性和循环寿命。",
      "keyPoints": ["BESS", "最优控制", "循环寿命"],
      "bmsValue": ["电网调度", "经济运行"],
      "imageUrl": "./images/energy-storage-bms-cloud-edge-digital-twin-architecture.jpg"
    }
  ],
  "history": [
    {
      "date": "2026-03-14",
      "papers": [
        {
          "id": 301,
          "category": "新材料体系",
          "title": "延展性SEI实现高性能固态电池",
          "source": "Nature Energy | 2026年3月",
          "doi": "10.1038/s41560-026-00123-x",
          "publishDate": "2026-03-10",
          "views": 3245,
          "summary": "首次提出延展性SEI设计策略，在15mA/cm²电流密度下循环4500小时。",
          "keyPoints": ["延展性SEI", "4500h循环", "-30°C运行"],
          "bmsValue": ["界面监测", "低温策略"],
          "imageUrl": "./images/sei-interface-formation-mechanism-diagram.jpg"
        },
        {
          "id": 302,
          "category": "SOH估算",
          "title": "基于MLP的深度学习循环SOH估计方法",
          "source": "JPS | 2026年2月",
          "doi": "10.1016/j.jpowsour.2026.234567",
          "publishDate": "2026-02-28",
          "views": 2156,
          "summary": "轻量化MLP模型，RMSE仅0.0069，适合嵌入式BMS。",
          "keyPoints": ["MLP", "RMSE 0.0069", "嵌入式"],
          "bmsValue": ["车载BMS", "低成本"],
          "imageUrl": "./images/mlp-neural-network-battery-soh-estimation-diagram.jpg"
        },
        {
          "id": 303,
          "category": "电池模型",
          "title": "多尺度电化学-机械耦合建模",
          "source": "Electrochimica Acta | 2026年3月",
          "doi": "10.1016/j.electacta.2026.135789",
          "publishDate": "2026-03-05",
          "views": 1876,
          "summary": "多尺度电化学-机械耦合模型，电压预测MAPE<1%。",
          "keyPoints": ["电化学-机械", "MAPE<1%"],
          "bmsValue": ["安全阈值", "膨胀力"],
          "imageUrl": "./images/electrochemical-battery-modeling-simulation-diagram.jpg"
        },
        {
          "id": 304,
          "category": "EIS检测",
          "title": "基于弛豫电压信号的在线全频EIS生成方法",
          "source": "IEEE TPEL | 2026年2月",
          "doi": "10.1109/TPEL.2026.2345678",
          "publishDate": "2026-02-20",
          "views": 1543,
          "summary": "通过弛豫电压信号重构全频阻抗谱。",
          "keyPoints": ["弛豫电压", "在线EIS"],
          "bmsValue": ["无设备EIS"],
          "imageUrl": "./images/eis-electrochemical-impedance-spectroscopy-diagnosis.jpg"
        },
        {
          "id": 305,
          "category": "AI/BMS",
          "title": "T-RUNSAFE: 因果感知的热失控预测框架",
          "source": "Scientific Reports | 2026年3月",
          "doi": "10.1038/s41598-026-12345-x",
          "publishDate": "2026-03-08",
          "views": 2890,
          "summary": "首个因果感知的多模态热失控预测框架，AUC-ROC达0.965。",
          "keyPoints": ["因果推理", "Transformer", "AUC-ROC 0.965"],
          "bmsValue": ["热失控预警"],
          "imageUrl": "./images/battery-thermal-runaway-safety-warning.jpg"
        },
        {
          "id": 306,
          "category": "异常诊断",
          "title": "基于无监督学习的锂离子电池多模态故障诊断",
          "source": "Nature Communications | 2026年2月",
          "doi": "10.1038/s41467-026-12345-y",
          "publishDate": "2026-02-15",
          "views": 2134,
          "summary": "基于无监督学习的多模态诊断框架，实现微短路早期检测。",
          "keyPoints": ["无监督", "微短路检测"],
          "bmsValue": ["故障预警"],
          "imageUrl": "./images/battery-fault-diagnosis-machine-learning-framework.jpg"
        },
        {
          "id": 307,
          "category": "热失控",
          "title": "基于SOS的热失控预警方法",
          "source": "Communications Engineering | 2025年",
          "doi": "10.1038/s44172-025-00123-z",
          "publishDate": "2025-12-01",
          "views": 4500,
          "summary": "首次提出SOS概念，实现5小时超前预警。",
          "keyPoints": ["SOS", "5小时预警"],
          "bmsValue": ["安全评估"],
          "imageUrl": "./images/battery-thermal-runaway-safety-warning.jpg"
        },
        {
          "id": 308,
          "category": "储能BMS",
          "title": "智能储能电池管理系统研究",
          "source": "RSC Advances | 2025年",
          "doi": "10.1039/D5RA12345",
          "publishDate": "2025-11-01",
          "views": 890,
          "summary": "提出IBMS云边协同架构。",
          "keyPoints": ["云边协同"],
          "bmsValue": ["储能BMS"],
          "imageUrl": "./images/energy-storage-bms-cloud-edge-digital-twin-architecture.jpg"
        }
      ]
    },
    {
      "date": "2026-03-12",
      "papers": [
        {
          "id": 201,
          "category": "新材料体系",
          "title": "硫化物全固态电池界面兼容性研究综述",
          "source": "Energy Storage Materials | 2025年10月",
          "doi": "10.1016/j.ensm.2025.101234",
          "publishDate": "2025-10-01",
          "views": 1250,
          "summary": "分析硫化物全固态电池界面五大不稳定机制。",
          "keyPoints": ["界面稳定性"],
          "bmsValue": ["EIS监测"],
          "imageUrl": "./images/sei-interface-formation-mechanism-diagram.jpg"
        },
        {
          "id": 202,
          "category": "SOH估算",
          "title": "基于部分充电电压特征的SOH混合深度学习",
          "source": "汽车工程 | 2026年1月",
          "doi": "10.19562/j.chinasae.qcgc.2026.01.001",
          "publishDate": "2026-01-01",
          "views": 980,
          "summary": "COA-CNN-LSTM混合深度学习模型。",
          "keyPoints": ["CNN-LSTM"],
          "bmsValue": ["车载应用"],
          "imageUrl": "./images/mlp-neural-network-battery-soh-estimation-diagram.jpg"
        }
      ]
    }
  ]
}