{
  "updateDate": "2026-03-14",
  "currentPapers": [
    {
      "id": 1,
      "category": "新材料体系",
      "title": "延展性固体电解质界面实现高性能固态电池",
      "source": "Nature | 2025年10月",
      "doi": "10.1038/s41586-025-09675-8",
      "publishDate": "2025-10-29",
      "views": 20000,
      "summary": "首次报道延展性无机富集SEI，可在15 mA/cm²高电流密度和15 mAh/cm²面容量下实现超过4500小时循环寿命，-30°C低温下仍可工作7000小时。",
      "keyPoints": ["延展性SEI解决脆性SEI导致的锂枝晶问题", "Ag2S和AgF组分通过置换反应形成", "15 mA/cm²高电流密度下循环4500小时", "-30°C低温运行7000小时"],
      "bmsValue": ["固态电池界面工程对BMS参数设计有借鉴意义", "可探索将自适应机制应用于电池界面稳定性监测", "为未来固态电池BMS算法开发提供理论基础"],
      "imageUrl": ""
    },
    {
      "id": 2,
      "category": "SOH估算",
      "title": "基于深度学习的锂离子电池循环SOH估计",
      "source": "Scientific Reports (Nature) | 2025年10月",
      "doi": "10.1038/s41598-025-20995-7",
      "publishDate": "2025-10-23",
      "views": 4820,
      "summary": "评估MLP、GRU、LSTM和TCN四种深度学习模型，MLP在B0005数据集上取得最佳性能，RMSE 0.0069，MAE 0.0049，R²=0.9955，适合嵌入式BMS。",
      "keyPoints": ["MLP优于其他模型，RMSE仅0.0069", "TCN具有可比精度且计算效率高", "GRU和LSTM训练时间更长但精度无提升", "MLP推荐用于嵌入式BMS"],
      "bmsValue": ["MLP轻量化适合车载BMS部署", "深度学习有效捕捉非线性退化行为", "多数据集验证泛化能力"],
      "imageUrl": ""
    },
    {
      "id": 3,
      "category": "电池模型",
      "title": "锂离子电池高保真多尺度建模：跨尺度电化学-机械框架",
      "source": "Communications Engineering (Nature) | 2026年1月",
      "doi": "10.1038/s44172-025-00567-3",
      "publishDate": "2026-01-15",
      "views": 2496,
      "summary": "提出多尺度电化学-机械-热耦合建模框架，电压预测MAPE<1%，应变预测MAPE<3.6%，实现非破坏性参数辨识。",
      "keyPoints": ["耦合电化学反应与热效应", "电压-应变多目标参数辨识策略", "电压预测MAPE<1%", "粒子径向DIS最大压应力51 MPa"],
      "bmsValue": ["多物理场建模提升状态估计精度", "非破坏性参数辨识适用于在线估计", "数字孪生建立的基础"],
      "imageUrl": ""
    },
    {
      "id": 4,
      "category": "EIS检测",
      "title": "基于弛豫电压信号的在线全频电化学阻抗谱生成",
      "source": "Energy AI | 2025年",
      "doi": "10.1016/j.etran.2025.100265",
      "publishDate": "2025-09-01",
      "views": 890,
      "summary": "通过弛豫电压信号实现无硬件需求的在线全频EIS获取，为实时电池状态监测建立新范式。",
      "keyPoints": ["无需额外硬件的在线EIS测量", "弛豫电压信号用于EIS重建", "适用于实时电池状态监测"],
      "bmsValue": ["在线EIS监测提升SOH估计精度", "无硬件需求的低成本方案", "为车载EIS传感器集成提供可能"],
      "imageUrl": ""
    },
    {
      "id": 5,
      "category": "AI/BMS",
      "title": "时序感知Transformer网络用于无人机电池SOC多步预测",
      "source": "Scientific Reports (Nature) | 2026年1月",
      "doi": "10.1038/s41598-025-32347-6",
      "publishDate": "2026-01-20",
      "views": 3200,
      "summary": "提出TATNS混合深度学习框架，MAPE仅4.320%，比传统模型提升7.97%，推理延迟<10ms，支持60步未来预测。",
      "keyPoints": ["CNN+Transformer混合架构", "MAPE: 4.320%, MAE: 2.165", "推理延迟<10ms，适合边缘部署", "支持60步多步SOC预测"],
      "bmsValue": ["轻量化模型适合车载BMS", "多步预测支持能量管理优化", "低温(-10°C)下仍保持高精度"],
      "imageUrl": ""
    },
    {
      "id": 6,
      "category": "异常诊断",
      "title": "基于模型约束深度学习的锂离子电池随机条件在线故障诊断",
      "source": "Nature Communications | 2025年2月",
      "doi": "10.1038/s41467-025-56832-8",
      "publishDate": "2025-02-14",
      "views": 8500,
      "summary": "提出MCNN网络，在515辆车1820万条数据上验证，TPR提升46.5%，可诊断电解液泄漏、热失控、内短路、过老化四种故障。",
      "keyPoints": ["Model-constrained neural network (MCNN)", "电解液泄漏检出率97.76%", "热失控检出率89.60%", "6种输入特征即可部署"],
      "bmsValue": ["在线故障诊断适用于车队管理", "可迁移到不同结构电池包", "仅需电压、温度、电流等基本传感器"],
      "imageUrl": ""
    },
    {
      "id": 7,
      "category": "热失控",
      "title": "基于安全状态(SOS)的锂离子电池热失控预警",
      "source": "Communications Engineering (Nature) | 2025年6月",
      "doi": "10.1038/s44172-025-00442-1",
      "publishDate": "2025-06-10",
      "views": 12000,
      "summary": "首次提出SOS概念，多维参数融合实现热失控5小时超前预警，应变触发点比温度提前906秒。",
      "keyPoints": ["SOS=0-100%量化安全状态", "5小时超前预警能力", "应变信号比温度提前906秒", "五阶段热失控演化模型"],
      "bmsValue": ["多维参数融合提升预警可靠性", "超长预警时间为安全策略争取时间", "分级告警机制设计基础"],
      "imageUrl": ""
    },
    {
      "id": 8,
      "category": "储能BMS",
      "title": "端-边-云连接的智能电池管理系统(IBMS)综述",
      "source": "RSC Sustainable Energy Fuels | 2025年1月",
      "doi": "10.1039/D4SE01238K",
      "publishDate": "2025-01-22",
      "views": 5600,
      "summary": "提出三层架构IBMS，集成云计算、数字孪生、区块链和物联网，实现云边协同的电池管理。",
      "keyPoints": ["End-Edge-Cloud三层架构", "云端：数字孪生和大数据分析", "边缘：实时状态估计和安全控制", "可重构电池包技术"],
      "bmsValue": ["云边协同架构适合储能系统", "数字孪生支持预测性维护", "区块链保障电池全生命周期数据安全"],
      "imageUrl": ""
    }
  ],
  "history": [
    {
      "date": "2026-03-13",
      "papers": [
        {
          "id": 201,
          "category": "新材料体系",
          "title": "自适应界面实现无外压固态锂金属电池",
          "source": "Nature Sustainability | 2025年10月",
          "doi": "10.1038/s41893-025-01649-y",
          "publishDate": "2025-10-07",
          "views": 8868,
          "summary": "首次提出动态自适应界面(DAI)概念，通过固体电解质中预置阴离子的可控迁移形成自适应界面，使锂金属负极在零外压条件下稳定运行，2400次循环后容量保持率达90.7%。",
          "keyPoints": ["动态自适应界面(DAI)解决锂金属与固体电解质界面接触问题", "预置碘离子(I-)在电场驱动下迁移形成富碘自适应界面", "1.25 mA/cm²电流密度下2400次循环容量保持90.7%", "零外压软包电池300次循环后容量保持74.4%"],
          "bmsValue": ["固态电池界面工程对BMS参数设计有借鉴意义", "可探索将自适应机制应用于电池界面稳定性监测", "为未来固态电池BMS算法开发提供理论基础"],
          "imageUrl": "https://cdn.hailuoai.com/matrix_agent/20260313/image_tool/output/143458_6d5e/workspace/images/dai_solid_state.png"
        },
        {
          "id": 202,
          "category": "SOH估算",
          "title": "群智能优化深度神经网络的锂离子电池SOH智能诊断",
          "source": "Scientific Reports | 2025年12月",
          "doi": "10.1038/s41598-025-34022-2",
          "publishDate": "2025-12-30",
          "views": 1307,
          "summary": "提出多维间接健康指标(IHI)提取机制和基于麻雀搜索算法(SSA)优化的残差LSTM网络，MAE仅0.3060%。",
          "keyPoints": ["多维间接健康指标(IHI)：电压微分斜率、恒流充电时间，温度变化率", "SSA算法优化7个关键超参数", "残差校正机制补偿系统偏差", "MAE: 0.3060%, RMSE: 0.4641%, MAPE: 0.3600%"],
          "bmsValue": ["IHI特征提取可直接用于实际车载SOH估计", "SSA优化算法可推广到其他BMS算法调参", "残差校正思路可提升估计精度"],
          "imageUrl": "https://cdn.hailuoai.com/matrix_agent/20260313/image_tool/output/143511_861d/workspace/images/ssa_lstm_soh.png"
        }
      ]
    },
    {
      "date": "2026-03-12",
      "papers": [
        {
          "id": 101,
          "category": "新材料体系",
          "title": "硫化物全固态电池界面兼容性研究综述",
          "source": "Energy Storage Materials | 2025年10月",
          "doi": "10.1016/j.ensm.2025.104640",
          "publishDate": "2025-10-01",
          "views": 1250,
          "summary": "系统分析了硫化物全固态电池中正极-电解质和负极-电解质界面的五大不稳定机制，并提出了界面工程策略。",
          "keyPoints": ["热力学不稳定", "化学活性", "电化学动力学", "机械不匹配", "材料兼容性不足"],
          "bmsValue": ["EIS在线监测界面阻抗变化", "电流密度和过电位关系辅助充电策略", "界面退化诊断"],
          "imageUrl": "https://cdn.hailuoai.com/matrix_agent/20260312/image_tool/output/211509_83c3/workspace/images/solid_state_interface.png"
        },
        {
          "id": 102,
          "category": "SOH估算",
          "title": "基于部分充电电压特征的锂电池SOH混合深度学习估计方法",
          "source": "汽车工程 | 2026年1月",
          "doi": "10.19562/j.chinasae.qcgc.2026.01.011",
          "publishDate": "2026-01-01",
          "views": 980,
          "summary": "提出COA-CNN-LSTM混合深度学习模型，仅用0.1V电压片段即可实现高精度SOH估计。",
          "keyPoints": ["CNN-LSTM混合模型", "COA优化算法", "4个关键特征"],
          "bmsValue": ["部分数据估计适合车载应用", "COA优化推广到其他算法"],
          "imageUrl": "https://cdn.hailuoai.com/matrix_agent/20260312/image_tool/output/211437_7b6e/workspace/images/coa_cnn_lstm_soh.png"
        }
      ]
    }
  ]
}
